{
"meta":{"test_sets":[],"test_metrics":[],"learn_metrics":[{"best_value":"Min","name":"Logloss"}],"launch_mode":"Train","parameters":"","iteration_count":500,"learn_sets":["learn"],"name":"experiment"},
"iterations":[
{"learn":[0.3924237372],"iteration":0,"passed_time":0.01251894306,"remaining_time":6.246952588},
{"learn":[0.2202824057],"iteration":1,"passed_time":0.02363672032,"remaining_time":5.885543361},
{"learn":[0.1165475378],"iteration":2,"passed_time":0.03479628764,"remaining_time":5.764584986},
{"learn":[0.06798443709],"iteration":3,"passed_time":0.04514226936,"remaining_time":5.597641401},
{"learn":[0.04017951717],"iteration":4,"passed_time":0.0552558487,"remaining_time":5.470329021},
{"learn":[0.02596118867],"iteration":5,"passed_time":0.06508223834,"remaining_time":5.358437624},
{"learn":[0.01743706605],"iteration":6,"passed_time":0.07533786845,"remaining_time":5.305938449},
{"learn":[0.01238685546],"iteration":7,"passed_time":0.08529621235,"remaining_time":5.245717059},
{"learn":[0.009375104219],"iteration":8,"passed_time":0.09512739918,"remaining_time":5.189728111},
{"learn":[0.007495793449],"iteration":9,"passed_time":0.1050431009,"remaining_time":5.147111945},
{"learn":[0.006273701005],"iteration":10,"passed_time":0.1148657261,"remaining_time":5.106303642},
{"learn":[0.005402510169],"iteration":11,"passed_time":0.1249965231,"remaining_time":5.083191939},
{"learn":[0.004803712762],"iteration":12,"passed_time":0.1355607115,"remaining_time":5.078312806},
{"learn":[0.004320927308],"iteration":13,"passed_time":0.1468045216,"remaining_time":5.096214108},
{"learn":[0.00398752971],"iteration":14,"passed_time":0.1575880408,"remaining_time":5.095346653},
{"learn":[0.00377673851],"iteration":15,"passed_time":0.167386229,"remaining_time":5.063433427},
{"learn":[0.003581052022],"iteration":16,"passed_time":0.1784824024,"remaining_time":5.071000022},
{"learn":[0.003366953843],"iteration":17,"passed_time":0.1908327415,"remaining_time":5.110076746},
{"learn":[0.003215378326],"iteration":18,"passed_time":0.2020220568,"remaining_time":5.11434786},
{"learn":[0.00309864553],"iteration":19,"passed_time":0.212337708,"remaining_time":5.096104991},
{"learn":[0.003005467068],"iteration":20,"passed_time":0.2223777223,"remaining_time":5.072329951},
{"learn":[0.002936968949],"iteration":21,"passed_time":0.2336088357,"remaining_time":5.075682885},
{"learn":[0.002895380722],"iteration":22,"passed_time":0.2444282472,"remaining_time":5.0692293},
{"learn":[0.002854959516],"iteration":23,"passed_time":0.2544941746,"remaining_time":5.047467796},
{"learn":[0.002828911386],"iteration":24,"passed_time":0.2647322742,"remaining_time":5.029913211},
{"learn":[0.002776040687],"iteration":25,"passed_time":0.2752923899,"remaining_time":5.018792031},
{"learn":[0.002749911498],"iteration":26,"passed_time":0.2851227036,"remaining_time":4.994927363},
{"learn":[0.002713208492],"iteration":27,"passed_time":0.2958230889,"remaining_time":4.986732071},
{"learn":[0.002689101617],"iteration":28,"passed_time":0.3071645767,"remaining_time":4.988776401},
{"learn":[0.002672766879],"iteration":29,"passed_time":0.3178963069,"remaining_time":4.980375475},
{"learn":[0.002652280258],"iteration":30,"passed_time":0.3278655639,"remaining_time":4.960288692},
{"learn":[0.0026361992],"iteration":31,"passed_time":0.3381388475,"remaining_time":4.945280645},
{"learn":[0.002602295269],"iteration":32,"passed_time":0.348739104,"remaining_time":4.935186714},
{"learn":[0.002579729732],"iteration":33,"passed_time":0.3597982477,"remaining_time":4.931352454},
{"learn":[0.002572431422],"iteration":34,"passed_time":0.3698690043,"remaining_time":4.913973914},
{"learn":[0.00256079547],"iteration":35,"passed_time":0.379774868,"remaining_time":4.894876077},
{"learn":[0.002537130386],"iteration":36,"passed_time":0.3907672108,"remaining_time":4.889870773},
{"learn":[0.002523491919],"iteration":37,"passed_time":0.400806142,"remaining_time":4.872958884},
{"learn":[0.002506460393],"iteration":38,"passed_time":0.4116927538,"remaining_time":4.866419475},
{"learn":[0.002493066149],"iteration":39,"passed_time":0.4218854163,"remaining_time":4.851682287},
{"learn":[0.00248192046],"iteration":40,"passed_time":0.4316423679,"remaining_time":4.832288948},
{"learn":[0.002471955703],"iteration":41,"passed_time":0.4417719632,"remaining_time":4.817418075},
{"learn":[0.00246687712],"iteration":42,"passed_time":0.4515349056,"remaining_time":4.798870974},
{"learn":[0.002452586831],"iteration":43,"passed_time":0.4615589803,"remaining_time":4.783429432},
{"learn":[0.002439956014],"iteration":44,"passed_time":0.4727527942,"remaining_time":4.78005603},
{"learn":[0.002435940191],"iteration":45,"passed_time":0.482756205,"remaining_time":4.764593849},
{"learn":[0.002426597066],"iteration":46,"passed_time":0.4935560493,"remaining_time":4.75704022},
{"learn":[0.002418397229],"iteration":47,"passed_time":0.5037748278,"remaining_time":4.743879628},
{"learn":[0.002404223674],"iteration":48,"passed_time":0.5144184751,"remaining_time":4.734749638},
{"learn":[0.002396780044],"iteration":49,"passed_time":0.5248203831,"remaining_time":4.723383448},
{"learn":[0.002388408063],"iteration":50,"passed_time":0.5354257466,"remaining_time":4.713846279},
{"learn":[0.002382217041],"iteration":51,"passed_time":0.5452658215,"remaining_time":4.69767477},
{"learn":[0.002377159761],"iteration":52,"passed_time":0.5554198286,"remaining_time":4.684389875},
{"learn":[0.002360173413],"iteration":53,"passed_time":0.5661159108,"remaining_time":4.675698078},
{"learn":[0.002343385241],"iteration":54,"passed_time":0.576919686,"remaining_time":4.667804732},
{"learn":[0.002334847574],"iteration":55,"passed_time":0.5870723,"remaining_time":4.654644665},
{"learn":[0.002330162236],"iteration":56,"passed_time":0.5974723449,"remaining_time":4.643513137},
{"learn":[0.002317626338],"iteration":57,"passed_time":0.6077203114,"remaining_time":4.63124789},
{"learn":[0.002312065921],"iteration":58,"passed_time":0.6185016944,"remaining_time":4.623038088},
{"learn":[0.002304997287],"iteration":59,"passed_time":0.6284099838,"remaining_time":4.608339881},
{"learn":[0.002292541893],"iteration":60,"passed_time":0.6398487599,"remaining_time":4.604813206},
{"learn":[0.002288179803],"iteration":61,"passed_time":0.6498820414,"remaining_time":4.591102164},
{"learn":[0.002279161257],"iteration":62,"passed_time":0.66008173,"remaining_time":4.578662159},
{"learn":[0.002273183625],"iteration":63,"passed_time":0.6704190855,"remaining_time":4.56723002},
{"learn":[0.002266849497],"iteration":64,"passed_time":0.680497748,"remaining_time":4.554100314},
{"learn":[0.002253730405],"iteration":65,"passed_time":0.6923899492,"remaining_time":4.552988454},
{"learn":[0.002243943315],"iteration":66,"passed_time":0.7032882095,"remaining_time":4.545131264},
{"learn":[0.002237535444],"iteration":67,"passed_time":0.7129116058,"remaining_time":4.529085496},
{"learn":[0.002231554147],"iteration":68,"passed_time":0.722945046,"remaining_time":4.515787171},
{"learn":[0.002227659673],"iteration":69,"passed_time":0.7327996,"remaining_time":4.501483257},
{"learn":[0.002224207706],"iteration":70,"passed_time":0.7431584461,"remaining_time":4.490351738},
{"learn":[0.002213810681],"iteration":71,"passed_time":0.7532685124,"remaining_time":4.477762824},
{"learn":[0.002210037088],"iteration":72,"passed_time":0.7634169881,"remaining_time":4.465466492},
{"learn":[0.00220481986],"iteration":73,"passed_time":0.7731773058,"remaining_time":4.450993679},
{"learn":[0.002193248059],"iteration":74,"passed_time":0.7836831418,"remaining_time":4.440871137},
{"learn":[0.002182479625],"iteration":75,"passed_time":0.7942499488,"remaining_time":4.431078662},
{"learn":[0.002175918485],"iteration":76,"passed_time":0.8046997896,"remaining_time":4.42062352},
{"learn":[0.002167104002],"iteration":77,"passed_time":0.8154040806,"remaining_time":4.411545154},
{"learn":[0.002162779417],"iteration":78,"passed_time":0.8256681945,"remaining_time":4.400079872},
{"learn":[0.002155509556],"iteration":79,"passed_time":0.8359602756,"remaining_time":4.388791447},
{"learn":[0.002150623015],"iteration":80,"passed_time":0.8462455958,"remaining_time":4.37749265},
{"learn":[0.00214099079],"iteration":81,"passed_time":0.8573088992,"remaining_time":4.370184389},
{"learn":[0.002134252659],"iteration":82,"passed_time":0.8672735299,"remaining_time":4.357265807},
{"learn":[0.002128273805],"iteration":83,"passed_time":0.877876935,"remaining_time":4.347581011},
{"learn":[0.002124612459],"iteration":84,"passed_time":0.8876875177,"remaining_time":4.334003763},
{"learn":[0.002118608083],"iteration":85,"passed_time":0.8982208094,"remaining_time":4.323993199},
{"learn":[0.002112551839],"iteration":86,"passed_time":0.9093264835,"remaining_time":4.31668779},
{"learn":[0.00210814365],"iteration":87,"passed_time":0.9201193644,"remaining_time":4.30783157},
{"learn":[0.002101441347],"iteration":88,"passed_time":0.9305358986,"remaining_time":4.297193869},
{"learn":[0.002095836976],"iteration":89,"passed_time":0.9407528711,"remaining_time":4.285651968},
{"learn":[0.002079307049],"iteration":90,"passed_time":0.9523003357,"remaining_time":4.280119091},
{"learn":[0.002071670868],"iteration":91,"passed_time":0.9627358011,"remaining_time":4.269523988},
{"learn":[0.002064684196],"iteration":92,"passed_time":0.9735186876,"remaining_time":4.260452751},
{"learn":[0.002053149138],"iteration":93,"passed_time":0.9845441558,"remaining_time":4.252392843},
{"learn":[0.002050902619],"iteration":94,"passed_time":0.9944417952,"remaining_time":4.23946239},
{"learn":[0.002040535828],"iteration":95,"passed_time":1.004636912,"remaining_time":4.227847005},
{"learn":[0.002037646581],"iteration":96,"passed_time":1.01588557,"remaining_time":4.220637988},
{"learn":[0.002029072826],"iteration":97,"passed_time":1.026429599,"remaining_time":4.21045611},
{"learn":[0.00201672987],"iteration":98,"passed_time":1.037159003,"remaining_time":4.201017782},
{"learn":[0.002011427982],"iteration":99,"passed_time":1.047466441,"remaining_time":4.189865763},
{"learn":[0.00200479323],"iteration":100,"passed_time":1.057713122,"remaining_time":4.178490454},
{"learn":[0.002001215461],"iteration":101,"passed_time":1.06820135,"remaining_time":4.168079777},
{"learn":[0.001995762176],"iteration":102,"passed_time":1.078753124,"remaining_time":4.157912527},
{"learn":[0.001989337237],"iteration":103,"passed_time":1.090179653,"remaining_time":4.15106868},
{"learn":[0.001982437182],"iteration":104,"passed_time":1.100272545,"remaining_time":4.139120527},
{"learn":[0.001977167129],"iteration":105,"passed_time":1.110471028,"remaining_time":4.12759986},
{"learn":[0.001963756611],"iteration":106,"passed_time":1.120803247,"remaining_time":4.116595104},
{"learn":[0.001958793283],"iteration":107,"passed_time":1.131670587,"remaining_time":4.107545095},
{"learn":[0.001953989115],"iteration":108,"passed_time":1.14197028,"remaining_time":4.096425501},
{"learn":[0.001950757865],"iteration":109,"passed_time":1.15246068,"remaining_time":4.085996957},
{"learn":[0.001943155988],"iteration":110,"passed_time":1.162365412,"remaining_time":4.073514821},
{"learn":[0.001940895771],"iteration":111,"passed_time":1.173168563,"remaining_time":4.064191094},
{"learn":[0.001932297107],"iteration":112,"passed_time":1.184100573,"remaining_time":4.055282492},
{"learn":[0.001924952937],"iteration":113,"passed_time":1.1950671,"remaining_time":4.046455269},
{"learn":[0.001922490227],"iteration":114,"passed_time":1.20620582,"remaining_time":4.038167312},
{"learn":[0.001915171505],"iteration":115,"passed_time":1.216382975,"remaining_time":4.026647089},
{"learn":[0.001905540287],"iteration":116,"passed_time":1.226787057,"remaining_time":4.015892673},
{"learn":[0.00190320534],"iteration":117,"passed_time":1.237047394,"remaining_time":4.004678853},
{"learn":[0.001897983979],"iteration":118,"passed_time":1.248003195,"remaining_time":3.995707709},
{"learn":[0.001893100244],"iteration":119,"passed_time":1.258091179,"remaining_time":3.983955401},
{"learn":[0.001888443035],"iteration":120,"passed_time":1.268422157,"remaining_time":3.972991716},
{"learn":[0.001885605456],"iteration":121,"passed_time":1.278668299,"remaining_time":3.96177555},
{"learn":[0.001881794915],"iteration":122,"passed_time":1.288880896,"remaining_time":3.950472339},
{"learn":[0.001878131363],"iteration":123,"passed_time":1.299004711,"remaining_time":3.93891751},
{"learn":[0.00187299743],"iteration":124,"passed_time":1.309441063,"remaining_time":3.92832319},
{"learn":[0.001869367565],"iteration":125,"passed_time":1.319363733,"remaining_time":3.916206635},
{"learn":[0.001861977284],"iteration":126,"passed_time":1.329667914,"remaining_time":3.905245134},
{"learn":[0.001859873047],"iteration":127,"passed_time":1.339518165,"remaining_time":3.892974667},
{"learn":[0.00185564489],"iteration":128,"passed_time":1.34990145,"remaining_time":3.882274712},
{"learn":[0.001853578542],"iteration":129,"passed_time":1.359870622,"remaining_time":3.870401002},
{"learn":[0.001845302567],"iteration":130,"passed_time":1.370267642,"remaining_time":3.859761526},
{"learn":[0.001837473255],"iteration":131,"passed_time":1.380841282,"remaining_time":3.849618121},
{"learn":[0.001830711562],"iteration":132,"passed_time":1.391051382,"remaining_time":3.838465091},
{"learn":[0.001826021954],"iteration":133,"passed_time":1.401849818,"remaining_time":3.828933085},
{"learn":[0.001818199536],"iteration":134,"passed_time":1.412326132,"remaining_time":3.818511395},
{"learn":[0.001809074915],"iteration":135,"passed_time":1.42266309,"remaining_time":3.807715917},
{"learn":[0.00180667974],"iteration":136,"passed_time":1.432910245,"remaining_time":3.796689188},
{"learn":[0.001801202996],"iteration":137,"passed_time":1.442977781,"remaining_time":3.785202584},
{"learn":[0.001796002285],"iteration":138,"passed_time":1.45330758,"remaining_time":3.774417529},
{"learn":[0.001786436322],"iteration":139,"passed_time":1.464387226,"remaining_time":3.765567153},
{"learn":[0.001782943055],"iteration":140,"passed_time":1.474930128,"remaining_time":3.755318553},
{"learn":[0.001778209814],"iteration":141,"passed_time":1.484968844,"remaining_time":3.743794692},
{"learn":[0.001775993],"iteration":142,"passed_time":1.495104012,"remaining_time":3.732532393},
{"learn":[0.001772459084],"iteration":143,"passed_time":1.505013884,"remaining_time":3.720728768},
{"learn":[0.00176925426],"iteration":144,"passed_time":1.515672068,"remaining_time":3.710783338},
{"learn":[0.0017673077],"iteration":145,"passed_time":1.525987789,"remaining_time":3.69999779},
{"learn":[0.00176175866],"iteration":146,"passed_time":1.536735476,"remaining_time":3.690255939},
{"learn":[0.001753765523],"iteration":147,"passed_time":1.547409567,"remaining_time":3.680325457},
{"learn":[0.001749864074],"iteration":148,"passed_time":1.55808547,"remaining_time":3.670389262},
{"learn":[0.001746491774],"iteration":149,"passed_time":1.568287908,"remaining_time":3.659338453},
{"learn":[0.001744762584],"iteration":150,"passed_time":1.57909167,"remaining_time":3.649688695},
{"learn":[0.00173278242],"iteration":151,"passed_time":1.59162111,"remaining_time":3.643974647},
{"learn":[0.001727343895],"iteration":152,"passed_time":1.603132929,"remaining_time":3.635863571},
{"learn":[0.001725725738],"iteration":153,"passed_time":1.613831039,"remaining_time":3.625880126},
{"learn":[0.00172227463],"iteration":154,"passed_time":1.624872565,"remaining_time":3.616651839},
{"learn":[0.001712030445],"iteration":155,"passed_time":1.637247497,"remaining_time":3.610340634},
{"learn":[0.001710672226],"iteration":156,"passed_time":1.648456702,"remaining_time":3.601405407},
{"learn":[0.00170787018],"iteration":157,"passed_time":1.659516042,"remaining_time":3.592117002},
{"learn":[0.001702524757],"iteration":158,"passed_time":1.670521065,"remaining_time":3.582689831},
{"learn":[0.001700105307],"iteration":159,"passed_time":1.681719966,"remaining_time":3.573654928},
{"learn":[0.001695505932],"iteration":160,"passed_time":1.694970876,"remaining_time":3.568913832},
{"learn":[0.001689118521],"iteration":161,"passed_time":1.706717862,"remaining_time":3.560929859},
{"learn":[0.001685193814],"iteration":162,"passed_time":1.718156892,"remaining_time":3.552263022},
{"learn":[0.001680650533],"iteration":163,"passed_time":1.729519692,"remaining_time":3.543406198},
{"learn":[0.001679109471],"iteration":164,"passed_time":1.740650801,"remaining_time":3.534048595},
{"learn":[0.001675714806],"iteration":165,"passed_time":1.751712199,"remaining_time":3.524529365},
{"learn":[0.001668704343],"iteration":166,"passed_time":1.76383385,"remaining_time":3.51710582},
{"learn":[0.001662393945],"iteration":167,"passed_time":1.775634895,"remaining_time":3.508992768},
{"learn":[0.001657925849],"iteration":168,"passed_time":1.788368115,"remaining_time":3.502661811},
{"learn":[0.001654254743],"iteration":169,"passed_time":1.798769172,"remaining_time":3.491728392},
{"learn":[0.001650242967],"iteration":170,"passed_time":1.809212071,"remaining_time":3.480881703},
{"learn":[0.001643581666],"iteration":171,"passed_time":1.819925747,"remaining_time":3.470556076},
{"learn":[0.001637123436],"iteration":172,"passed_time":1.830305138,"remaining_time":3.459594105},
{"learn":[0.001635475512],"iteration":173,"passed_time":1.841274189,"remaining_time":3.449743595},
{"learn":[0.001631509046],"iteration":174,"passed_time":1.852296752,"remaining_time":3.439979682},
{"learn":[0.001627601237],"iteration":175,"passed_time":1.862653775,"remaining_time":3.428976267},
{"learn":[0.001624104284],"iteration":176,"passed_time":1.873371189,"remaining_time":3.418637819},
{"learn":[0.001623071174],"iteration":177,"passed_time":1.88424544,"remaining_time":3.40857883},
{"learn":[0.001620102848],"iteration":178,"passed_time":1.894330029,"remaining_time":3.397094632},
{"learn":[0.001619219886],"iteration":179,"passed_time":1.904478867,"remaining_time":3.385740207},
{"learn":[0.001615072067],"iteration":180,"passed_time":1.915079862,"remaining_time":3.375196},
{"learn":[0.001611413623],"iteration":181,"passed_time":1.925110671,"remaining_time":3.363654908},
{"learn":[0.001609528726],"iteration":182,"passed_time":1.935568079,"remaining_time":3.352869295},
{"learn":[0.0016087467],"iteration":183,"passed_time":1.945961587,"remaining_time":3.341977507},
{"learn":[0.001605536013],"iteration":184,"passed_time":1.956484841,"remaining_time":3.331312026},
{"learn":[0.001603921327],"iteration":185,"passed_time":1.966673427,"remaining_time":3.320083097},
{"learn":[0.00160037586],"iteration":186,"passed_time":1.977428214,"remaining_time":3.309813},
{"learn":[0.001597527574],"iteration":187,"passed_time":1.987595278,"remaining_time":3.298562376},
{"learn":[0.001593958958],"iteration":188,"passed_time":1.998530346,"remaining_time":3.288586972},
{"learn":[0.00158847001],"iteration":189,"passed_time":2.009000021,"remaining_time":3.277842139},
{"learn":[0.001587040489],"iteration":190,"passed_time":2.019611725,"remaining_time":3.267329964},
{"learn":[0.001586381303],"iteration":191,"passed_time":2.030027296,"remaining_time":3.256502121},
{"learn":[0.001585796911],"iteration":192,"passed_time":2.040105254,"remaining_time":3.245141518},
{"learn":[0.001577589513],"iteration":193,"passed_time":2.051827194,"remaining_time":3.236387224},
{"learn":[0.001573211954],"iteration":194,"passed_time":2.062753031,"remaining_time":3.226357305},
{"learn":[0.001570521906],"iteration":195,"passed_time":2.073447596,"remaining_time":3.215959537},
{"learn":[0.001567607588],"iteration":196,"passed_time":2.083948244,"remaining_time":3.205260496},
{"learn":[0.001564427697],"iteration":197,"passed_time":2.094914961,"remaining_time":3.195274334},
{"learn":[0.001556988838],"iteration":198,"passed_time":2.105538445,"remaining_time":3.184759156},
{"learn":[0.001553821896],"iteration":199,"passed_time":2.115972558,"remaining_time":3.173958836},
{"learn":[0.001548866247],"iteration":200,"passed_time":2.126201093,"remaining_time":3.162856352},
{"learn":[0.001545776048],"iteration":201,"passed_time":2.136861098,"remaining_time":3.152399046},
{"learn":[0.001541250285],"iteration":202,"passed_time":2.14763021,"remaining_time":3.142099371},
{"learn":[0.001538063254],"iteration":203,"passed_time":2.158198753,"remaining_time":3.131504073},
{"learn":[0.001535353667],"iteration":204,"passed_time":2.168936792,"remaining_time":3.121152944},
{"learn":[0.001533483371],"iteration":205,"passed_time":2.179187241,"remaining_time":3.11010218},
{"learn":[0.001530862533],"iteration":206,"passed_time":2.189747979,"remaining_time":3.099498348},
{"learn":[0.00152853955],"iteration":207,"passed_time":2.200371664,"remaining_time":3.088983298},
{"learn":[0.001526690171],"iteration":208,"passed_time":2.210561242,"remaining_time":3.077862781},
{"learn":[0.001524132113],"iteration":209,"passed_time":2.221339539,"remaining_time":3.067564126},
{"learn":[0.001521869382],"iteration":210,"passed_time":2.231620703,"remaining_time":3.056580016},
{"learn":[0.001513233142],"iteration":211,"passed_time":2.242589195,"remaining_time":3.046536265},
{"learn":[0.001510686055],"iteration":212,"passed_time":2.252824878,"remaining_time":3.035496432},
{"learn":[0.001503798482],"iteration":213,"passed_time":2.263994763,"remaining_time":3.025712627},
{"learn":[0.001502229253],"iteration":214,"passed_time":2.274048488,"remaining_time":3.014436368},
{"learn":[0.001499564317],"iteration":215,"passed_time":2.284144497,"remaining_time":3.003227024},
{"learn":[0.001497391454],"iteration":216,"passed_time":2.29473702,"remaining_time":2.992675468},
{"learn":[0.001493946505],"iteration":217,"passed_time":2.304979728,"remaining_time":2.981671024},
{"learn":[0.001490685367],"iteration":218,"passed_time":2.315330187,"remaining_time":2.970811792},
{"learn":[0.001487661724],"iteration":219,"passed_time":2.32572337,"remaining_time":2.960011562},
{"learn":[0.001487185164],"iteration":220,"passed_time":2.335736578,"remaining_time":2.948735318},
{"learn":[0.001484297911],"iteration":221,"passed_time":2.346273867,"remaining_time":2.938126734},
{"learn":[0.001482504017],"iteration":222,"passed_time":2.356637586,"remaining_time":2.927303189},
{"learn":[0.001477135808],"iteration":223,"passed_time":2.367466163,"remaining_time":2.917056522},
{"learn":[0.001475436981],"iteration":224,"passed_time":2.377367329,"remaining_time":2.905671179},
{"learn":[0.001473777093],"iteration":225,"passed_time":2.387581378,"remaining_time":2.894678307},
{"learn":[0.001469512902],"iteration":226,"passed_time":2.398764213,"remaining_time":2.884857401},
{"learn":[0.001467827745],"iteration":227,"passed_time":2.409256045,"remaining_time":2.874200194},
{"learn":[0.001466341089],"iteration":228,"passed_time":2.419816542,"remaining_time":2.86362569},
{"learn":[0.001463281456],"iteration":229,"passed_time":2.430153751,"remaining_time":2.852789186},
{"learn":[0.001461191037],"iteration":230,"passed_time":2.440963642,"remaining_time":2.842507445},
{"learn":[0.001458595237],"iteration":231,"passed_time":2.451649922,"remaining_time":2.832078358},
{"learn":[0.001457232795],"iteration":232,"passed_time":2.461739731,"remaining_time":2.820963555},
{"learn":[0.001451885275],"iteration":233,"passed_time":2.472637853,"remaining_time":2.810776362},
{"learn":[0.001449646044],"iteration":234,"passed_time":2.482667909,"remaining_time":2.799604237},
{"learn":[0.001446316073],"iteration":235,"passed_time":2.493277995,"remaining_time":2.789090638},
{"learn":[0.001444240844],"iteration":236,"passed_time":2.503284847,"remaining_time":2.777906814},
{"learn":[0.001443054838],"iteration":237,"passed_time":2.513671379,"remaining_time":2.767150846},
{"learn":[0.001436403356],"iteration":238,"passed_time":2.524256327,"remaining_time":2.75661465},
{"learn":[0.001434563751],"iteration":239,"passed_time":2.534946987,"remaining_time":2.74619257},
{"learn":[0.001430003236],"iteration":240,"passed_time":2.545707114,"remaining_time":2.735842915},
{"learn":[0.001426333571],"iteration":241,"passed_time":2.556873541,"remaining_time":2.725923031},
{"learn":[0.00142023157],"iteration":242,"passed_time":2.568111741,"remaining_time":2.716068796},
{"learn":[0.001415938761],"iteration":243,"passed_time":2.578198041,"remaining_time":2.704994666},
{"learn":[0.001414222431],"iteration":244,"passed_time":2.588969779,"remaining_time":2.694642015},
{"learn":[0.001409639987],"iteration":245,"passed_time":2.599261358,"remaining_time":2.683790183},
{"learn":[0.001405102983],"iteration":246,"passed_time":2.609313452,"remaining_time":2.672697584},
{"learn":[0.001404346265],"iteration":247,"passed_time":2.619252483,"remaining_time":2.661498491},
{"learn":[0.001401169831],"iteration":248,"passed_time":2.629371359,"remaining_time":2.650490807},
{"learn":[0.001396912865],"iteration":249,"passed_time":2.639863872,"remaining_time":2.639863872},
{"learn":[0.001395174369],"iteration":250,"passed_time":2.650519582,"remaining_time":2.629399904},
{"learn":[0.001393928442],"iteration":251,"passed_time":2.660677534,"remaining_time":2.618444557},
{"learn":[0.001389269855],"iteration":252,"passed_time":2.670932452,"remaining_time":2.607590181},
{"learn":[0.001386782207],"iteration":253,"passed_time":2.681540641,"remaining_time":2.597082668},
{"learn":[0.00138134791],"iteration":254,"passed_time":2.691929357,"remaining_time":2.586363499},
{"learn":[0.001376625826],"iteration":255,"passed_time":2.702392509,"remaining_time":2.57571786},
{"learn":[0.00137080706],"iteration":256,"passed_time":2.713209913,"remaining_time":2.565408595},
{"learn":[0.001369023662],"iteration":257,"passed_time":2.723395545,"remaining_time":2.554502798},
{"learn":[0.001367504018],"iteration":258,"passed_time":2.733300338,"remaining_time":2.543341241},
{"learn":[0.001363433153],"iteration":259,"passed_time":2.744172075,"remaining_time":2.533081915},
{"learn":[0.001361316581],"iteration":260,"passed_time":2.754563163,"remaining_time":2.522377762},
{"learn":[0.001359780586],"iteration":261,"passed_time":2.764771071,"remaining_time":2.511509599},
{"learn":[0.001354293478],"iteration":262,"passed_time":2.77500358,"remaining_time":2.500668626},
{"learn":[0.001352970926],"iteration":263,"passed_time":2.784763057,"remaining_time":2.489409399},
{"learn":[0.001350926239],"iteration":264,"passed_time":2.794718347,"remaining_time":2.478335138},
{"learn":[0.00134869067],"iteration":265,"passed_time":2.805381628,"remaining_time":2.467892109},
{"learn":[0.001343896638],"iteration":266,"passed_time":2.816491721,"remaining_time":2.457837344},
{"learn":[0.001338302442],"iteration":267,"passed_time":2.82831877,"remaining_time":2.448395353},
{"learn":[0.001336801969],"iteration":268,"passed_time":2.83829406,"remaining_time":2.437345457},
{"learn":[0.001334443414],"iteration":269,"passed_time":2.848892054,"remaining_time":2.426833972},
{"learn":[0.001334102966],"iteration":270,"passed_time":2.859342951,"remaining_time":2.416197549},
{"learn":[0.00133281945],"iteration":271,"passed_time":2.869838963,"remaining_time":2.405600307},
{"learn":[0.001330602847],"iteration":272,"passed_time":2.880406704,"remaining_time":2.39506345},
{"learn":[0.001329814864],"iteration":273,"passed_time":2.890679622,"remaining_time":2.384283192},
{"learn":[0.00132430416],"iteration":274,"passed_time":2.901932754,"remaining_time":2.374308617},
{"learn":[0.001317351608],"iteration":275,"passed_time":2.912787825,"remaining_time":2.364001713},
{"learn":[0.001316371468],"iteration":276,"passed_time":2.923181951,"remaining_time":2.353319766},
{"learn":[0.00131388646],"iteration":277,"passed_time":2.933651173,"remaining_time":2.342699858},
{"learn":[0.001313487558],"iteration":278,"passed_time":2.943917141,"remaining_time":2.331920029},
{"learn":[0.001309753206],"iteration":279,"passed_time":2.95463769,"remaining_time":2.321501042},
{"learn":[0.001306514571],"iteration":280,"passed_time":2.964670241,"remaining_time":2.310543711},
{"learn":[0.001303140248],"iteration":281,"passed_time":2.975159396,"remaining_time":2.299945916},
{"learn":[0.001302779426],"iteration":282,"passed_time":2.985051337,"remaining_time":2.288890954},
{"learn":[0.001301009677],"iteration":283,"passed_time":2.994826861,"remaining_time":2.277755641},
{"learn":[0.001295303743],"iteration":284,"passed_time":3.00659515,"remaining_time":2.268133184},
{"learn":[0.001291044527],"iteration":285,"passed_time":3.017599364,"remaining_time":2.257923999},
{"learn":[0.001289658501],"iteration":286,"passed_time":3.027597255,"remaining_time":2.246962423},
{"learn":[0.001285839861],"iteration":287,"passed_time":3.038389565,"remaining_time":2.236592319},
{"learn":[0.001281071267],"iteration":288,"passed_time":3.049553628,"remaining_time":2.226490711},
{"learn":[0.001279868172],"iteration":289,"passed_time":3.060047154,"remaining_time":2.215896215},
{"learn":[0.001277835751],"iteration":290,"passed_time":3.069960992,"remaining_time":2.204886073},
{"learn":[0.001274654889],"iteration":291,"passed_time":3.080861727,"remaining_time":2.194586436},
{"learn":[0.001270933809],"iteration":292,"passed_time":3.09121864,"remaining_time":2.183898493},
{"learn":[0.001267259544],"iteration":293,"passed_time":3.102138298,"remaining_time":2.173607107},
{"learn":[0.001265710618],"iteration":294,"passed_time":3.112695658,"remaining_time":2.163059695},
{"learn":[0.001261646899],"iteration":295,"passed_time":3.124048413,"remaining_time":2.153060393},
{"learn":[0.001259466171],"iteration":296,"passed_time":3.134628771,"remaining_time":2.142524042},
{"learn":[0.001258699983],"iteration":297,"passed_time":3.14471759,"remaining_time":2.131654205},
{"learn":[0.001257283028],"iteration":298,"passed_time":3.154991482,"remaining_time":2.120914006},
{"learn":[0.001252855325],"iteration":299,"passed_time":3.167595132,"remaining_time":2.111730088},
{"learn":[0.001251344717],"iteration":300,"passed_time":3.183133199,"remaining_time":2.104463477},
{"learn":[0.001250642661],"iteration":301,"passed_time":3.196464915,"remaining_time":2.09569554},
{"learn":[0.00124684604],"iteration":302,"passed_time":3.212239315,"remaining_time":2.088485627},
{"learn":[0.00124509215],"iteration":303,"passed_time":3.225498129,"remaining_time":2.079597478},
{"learn":[0.001243812298],"iteration":304,"passed_time":3.238695748,"remaining_time":2.070641544},
{"learn":[0.001242592536],"iteration":305,"passed_time":3.252187475,"remaining_time":2.061844347},
{"learn":[0.001241030848],"iteration":306,"passed_time":3.265862654,"remaining_time":2.053131896},
{"learn":[0.001234214238],"iteration":307,"passed_time":3.279496905,"remaining_time":2.044361707},
{"learn":[0.001231010646],"iteration":308,"passed_time":3.294567722,"remaining_time":2.03644801},
{"learn":[0.001230514683],"iteration":309,"passed_time":3.307323124,"remaining_time":2.027069012},
{"learn":[0.001228385779],"iteration":310,"passed_time":3.320327715,"remaining_time":2.017819737},
{"learn":[0.001227197718],"iteration":311,"passed_time":3.331968635,"remaining_time":2.007724691},
{"learn":[0.001224793016],"iteration":312,"passed_time":3.343056043,"remaining_time":1.997289073},
{"learn":[0.001220982938],"iteration":313,"passed_time":3.354173527,"remaining_time":1.986867121},
{"learn":[0.001218016792],"iteration":314,"passed_time":3.364963085,"remaining_time":1.976248161},
{"learn":[0.001217571361],"iteration":315,"passed_time":3.375352556,"remaining_time":1.965395159},
{"learn":[0.001215322266],"iteration":316,"passed_time":3.385794538,"remaining_time":1.954575396},
{"learn":[0.001214392827],"iteration":317,"passed_time":3.395671799,"remaining_time":1.943434803},
{"learn":[0.001213284183],"iteration":318,"passed_time":3.405516129,"remaining_time":1.932283447},
{"learn":[0.001212094531],"iteration":319,"passed_time":3.415786986,"remaining_time":1.92138018},
{"learn":[0.001211115952],"iteration":320,"passed_time":3.426457455,"remaining_time":1.91070369},
{"learn":[0.001209615512],"iteration":321,"passed_time":3.436908376,"remaining_time":1.899905873},
{"learn":[0.00120718408],"iteration":322,"passed_time":3.447213149,"remaining_time":1.889030116},
{"learn":[0.001206242844],"iteration":323,"passed_time":3.457517531,"remaining_time":1.878157671},
{"learn":[0.001204002359],"iteration":324,"passed_time":3.470392572,"remaining_time":1.868672924},
{"learn":[0.001202919858],"iteration":325,"passed_time":3.48128314,"remaining_time":1.858108179},
{"learn":[0.00120152802],"iteration":326,"passed_time":3.491925033,"remaining_time":1.84740988},
{"learn":[0.001197330678],"iteration":327,"passed_time":3.503190232,"remaining_time":1.83703878},
{"learn":[0.001196442522],"iteration":328,"passed_time":3.513365143,"remaining_time":1.826095561},
{"learn":[0.001194832376],"iteration":329,"passed_time":3.524218881,"remaining_time":1.815506696},
{"learn":[0.001194477226],"iteration":330,"passed_time":3.534805709,"remaining_time":1.804779954},
{"learn":[0.00118962165],"iteration":331,"passed_time":3.545766892,"remaining_time":1.794243487},
{"learn":[0.001188146479],"iteration":332,"passed_time":3.557027078,"remaining_time":1.783854421},
{"learn":[0.001186026323],"iteration":333,"passed_time":3.567344883,"remaining_time":1.772991768},
{"learn":[0.001180922138],"iteration":334,"passed_time":3.578532415,"remaining_time":1.762560742},
{"learn":[0.001178308339],"iteration":335,"passed_time":3.588769284,"remaining_time":1.751661198},
{"learn":[0.001175015379],"iteration":336,"passed_time":3.59964661,"remaining_time":1.741075363},
{"learn":[0.001171936214],"iteration":337,"passed_time":3.610012401,"remaining_time":1.73024263},
{"learn":[0.001170873992],"iteration":338,"passed_time":3.621021697,"remaining_time":1.719718269},
{"learn":[0.001168760562],"iteration":339,"passed_time":3.631252023,"remaining_time":1.708824482},
{"learn":[0.001167847099],"iteration":340,"passed_time":3.641921975,"remaining_time":1.698139572},
{"learn":[0.0011658695],"iteration":341,"passed_time":3.653557652,"remaining_time":1.687900904},
{"learn":[0.001164481977],"iteration":342,"passed_time":3.664536629,"remaining_time":1.677353501},
{"learn":[0.001163204925],"iteration":343,"passed_time":3.674776872,"remaining_time":1.666468582},
{"learn":[0.001162349677],"iteration":344,"passed_time":3.685101821,"remaining_time":1.655625456},
{"learn":[0.001160354301],"iteration":345,"passed_time":3.696121688,"remaining_time":1.645094624},
{"learn":[0.001158859133],"iteration":346,"passed_time":3.706484401,"remaining_time":1.63427122},
{"learn":[0.001157027508],"iteration":347,"passed_time":3.71805797,"remaining_time":1.623979343},
{"learn":[0.001154294187],"iteration":348,"passed_time":3.729480603,"remaining_time":1.613614817},
{"learn":[0.001152205811],"iteration":349,"passed_time":3.740777673,"remaining_time":1.603190431},
{"learn":[0.001151949371],"iteration":350,"passed_time":3.751140525,"remaining_time":1.592364496},
{"learn":[0.001151656798],"iteration":351,"passed_time":3.761990834,"remaining_time":1.581746146},
{"learn":[0.001148129214],"iteration":352,"passed_time":3.774631393,"remaining_time":1.571871996},
{"learn":[0.001147283288],"iteration":353,"passed_time":3.784987743,"remaining_time":1.561040143},
{"learn":[0.0011459123],"iteration":354,"passed_time":3.796004386,"remaining_time":1.550480665},
{"learn":[0.001145072341],"iteration":355,"passed_time":3.806948076,"remaining_time":1.53988911},
{"learn":[0.001143946302],"iteration":356,"passed_time":3.817307301,"remaining_time":1.529061468},
{"learn":[0.001142082529],"iteration":357,"passed_time":3.827388764,"remaining_time":1.51812627},
{"learn":[0.001140912367],"iteration":358,"passed_time":3.837932665,"remaining_time":1.507377453},
{"learn":[0.001137728568],"iteration":359,"passed_time":3.84838081,"remaining_time":1.496592537},
{"learn":[0.001136040247],"iteration":360,"passed_time":3.858813631,"remaining_time":1.485803586},
{"learn":[0.001135804012],"iteration":361,"passed_time":3.868848345,"remaining_time":1.474864839},
{"learn":[0.00113503876],"iteration":362,"passed_time":3.879593606,"remaining_time":1.46419924},
{"learn":[0.001130588169],"iteration":363,"passed_time":3.890861967,"remaining_time":1.453728647},
{"learn":[0.001127268503],"iteration":364,"passed_time":3.901829458,"remaining_time":1.443142402},
{"learn":[0.001123029723],"iteration":365,"passed_time":3.912786978,"remaining_time":1.432550424},
{"learn":[0.00112280318],"iteration":366,"passed_time":3.923106957,"remaining_time":1.42172541},
{"learn":[0.001121038272],"iteration":367,"passed_time":3.935072554,"remaining_time":1.411493416},
{"learn":[0.001120180209],"iteration":368,"passed_time":3.946991936,"remaining_time":1.40123562},
{"learn":[0.00111885281],"iteration":369,"passed_time":3.956952864,"remaining_time":1.390280736},
{"learn":[0.001115227136],"iteration":370,"passed_time":3.967840332,"remaining_time":1.379653377},
{"learn":[0.001114164723],"iteration":371,"passed_time":3.977914262,"remaining_time":1.368744692},
{"learn":[0.001113973616],"iteration":372,"passed_time":3.988291259,"remaining_time":1.357943673},
{"learn":[0.001112482606],"iteration":373,"passed_time":3.998239295,"remaining_time":1.347000404},
{"learn":[0.001109465182],"iteration":374,"passed_time":4.008626148,"remaining_time":1.336208716},
{"learn":[0.001108380629],"iteration":375,"passed_time":4.019259177,"remaining_time":1.325500367},
{"learn":[0.001104075222],"iteration":376,"passed_time":4.029836203,"remaining_time":1.314774146},
{"learn":[0.001099934796],"iteration":377,"passed_time":4.041004033,"remaining_time":1.304239397},
{"learn":[0.001096105187],"iteration":378,"passed_time":4.051765803,"remaining_time":1.293571668},
{"learn":[0.001095928321],"iteration":379,"passed_time":4.062481644,"remaining_time":1.28288894},
{"learn":[0.001089704107],"iteration":380,"passed_time":4.073810297,"remaining_time":1.272397442},
{"learn":[0.001085442515],"iteration":381,"passed_time":4.084571958,"remaining_time":1.261726416},
{"learn":[0.00108471454],"iteration":382,"passed_time":4.094624873,"remaining_time":1.250838408},
{"learn":[0.001082116212],"iteration":383,"passed_time":4.104830167,"remaining_time":1.24000078},
{"learn":[0.001077354051],"iteration":384,"passed_time":4.116085804,"remaining_time":1.229480175},
{"learn":[0.001075715017],"iteration":385,"passed_time":4.126383366,"remaining_time":1.218672808},
{"learn":[0.00107546243],"iteration":386,"passed_time":4.136279313,"remaining_time":1.207750807},
{"learn":[0.001074503498],"iteration":387,"passed_time":4.147303045,"remaining_time":1.197159642},
{"learn":[0.001070387866],"iteration":388,"passed_time":4.158635417,"remaining_time":1.186654322},
{"learn":[0.001068847708],"iteration":389,"passed_time":4.169676383,"remaining_time":1.17606257},
{"learn":[0.001067340058],"iteration":390,"passed_time":4.180351696,"remaining_time":1.165366585},
{"learn":[0.001067177494],"iteration":391,"passed_time":4.190669952,"remaining_time":1.154572334},
{"learn":[0.001065932165],"iteration":392,"passed_time":4.201100827,"remaining_time":1.143811167},
{"learn":[0.001064416733],"iteration":393,"passed_time":4.210943375,"remaining_time":1.132893395},
{"learn":[0.001064202939],"iteration":394,"passed_time":4.22073759,"remaining_time":1.12196822},
{"learn":[0.00106405665],"iteration":395,"passed_time":4.231313495,"remaining_time":1.111254049},
{"learn":[0.00106229021],"iteration":396,"passed_time":4.241822494,"remaining_time":1.100523216},
{"learn":[0.001059195707],"iteration":397,"passed_time":4.252473487,"remaining_time":1.089829889},
{"learn":[0.001057446566],"iteration":398,"passed_time":4.263821783,"remaining_time":1.079313283},
{"learn":[0.001055711151],"iteration":399,"passed_time":4.273934716,"remaining_time":1.068483679},
{"learn":[0.001054778025],"iteration":400,"passed_time":4.285015828,"remaining_time":1.057896676},
{"learn":[0.001051904023],"iteration":401,"passed_time":4.295713132,"remaining_time":1.047213649},
{"learn":[0.001050785525],"iteration":402,"passed_time":4.305965637,"remaining_time":1.036423491},
{"learn":[0.001050250684],"iteration":403,"passed_time":4.316238792,"remaining_time":1.025640901},
{"learn":[0.001050056952],"iteration":404,"passed_time":4.326251772,"remaining_time":1.014799798},
{"learn":[0.001047214135],"iteration":405,"passed_time":4.336860102,"remaining_time":1.004100615},
{"learn":[0.001045975944],"iteration":406,"passed_time":4.347848426,"remaining_time":0.9934887068},
{"learn":[0.00104540367],"iteration":407,"passed_time":4.358205347,"remaining_time":0.9827325782},
{"learn":[0.001042619663],"iteration":408,"passed_time":4.368891368,"remaining_time":0.9720516247},
{"learn":[0.001041902555],"iteration":409,"passed_time":4.378892286,"remaining_time":0.9612202579},
{"learn":[0.00103874127],"iteration":410,"passed_time":4.389354014,"remaining_time":0.9504927183},
{"learn":[0.001037101803],"iteration":411,"passed_time":4.399704455,"remaining_time":0.939742699},
{"learn":[0.0010338935],"iteration":412,"passed_time":4.410372707,"remaining_time":0.9290615629},
{"learn":[0.001032191406],"iteration":413,"passed_time":4.421802531,"remaining_time":0.9185386899},
{"learn":[0.00102963078],"iteration":414,"passed_time":4.43218693,"remaining_time":0.907797323},
{"learn":[0.001026075267],"iteration":415,"passed_time":4.442828365,"remaining_time":0.8971095738},
{"learn":[0.001023897267],"iteration":416,"passed_time":4.453355857,"remaining_time":0.8863993672},
{"learn":[0.001022983821],"iteration":417,"passed_time":4.463364455,"remaining_time":0.8755882423},
{"learn":[0.001022522376],"iteration":418,"passed_time":4.473421557,"remaining_time":0.8647903249},
{"learn":[0.001020421959],"iteration":419,"passed_time":4.48451723,"remaining_time":0.8541937581},
{"learn":[0.001019679256],"iteration":420,"passed_time":4.494214916,"remaining_time":0.8433324901},
{"learn":[0.001018937559],"iteration":421,"passed_time":4.503881325,"remaining_time":0.8324709557},
{"learn":[0.001017649401],"iteration":422,"passed_time":4.514922746,"remaining_time":0.8218653698},
{"learn":[0.001016121203],"iteration":423,"passed_time":4.526010239,"remaining_time":0.8112659862},
{"learn":[0.00101297352],"iteration":424,"passed_time":4.536180006,"remaining_time":0.800502354},
{"learn":[0.001012589871],"iteration":425,"passed_time":4.545946104,"remaining_time":0.7896713889},
{"learn":[0.001010543139],"iteration":426,"passed_time":4.556228798,"remaining_time":0.7789337289},
{"learn":[0.001009914981],"iteration":427,"passed_time":4.566227662,"remaining_time":0.7681504479},
{"learn":[0.001004085373],"iteration":428,"passed_time":4.576628679,"remaining_time":0.7574373805},
{"learn":[0.00100369327],"iteration":429,"passed_time":4.58667313,"remaining_time":0.7466677188},
{"learn":[0.001000374505],"iteration":430,"passed_time":4.597764575,"remaining_time":0.7360690388},
{"learn":[0.0009982956819],"iteration":431,"passed_time":4.608187812,"remaining_time":0.7253628964},
{"learn":[0.0009950856831],"iteration":432,"passed_time":4.618104167,"remaining_time":0.7145796286},
{"learn":[0.0009924555805],"iteration":433,"passed_time":4.629296638,"remaining_time":0.7039944197},
{"learn":[0.0009904631666],"iteration":434,"passed_time":4.63971813,"remaining_time":0.6932912148},
{"learn":[0.0009870151142],"iteration":435,"passed_time":4.649883101,"remaining_time":0.6825516479},
{"learn":[0.0009839462116],"iteration":436,"passed_time":4.660540307,"remaining_time":0.6718856736},
{"learn":[0.0009829230148],"iteration":437,"passed_time":4.671473374,"remaining_time":0.6612587881},
{"learn":[0.0009800731049],"iteration":438,"passed_time":4.682470137,"remaining_time":0.6506393584},
{"learn":[0.0009799292061],"iteration":439,"passed_time":4.69253471,"remaining_time":0.6398910969},
{"learn":[0.0009776089566],"iteration":440,"passed_time":4.702569184,"remaining_time":0.629141909},
{"learn":[0.0009731316691],"iteration":441,"passed_time":4.713897086,"remaining_time":0.6185656809},
{"learn":[0.000970230407],"iteration":442,"passed_time":4.724250782,"remaining_time":0.6078607101},
{"learn":[0.0009668698054],"iteration":443,"passed_time":4.735181639,"remaining_time":0.5972301166},
{"learn":[0.0009656670337],"iteration":444,"passed_time":4.746347657,"remaining_time":0.5866272385},
{"learn":[0.0009623386909],"iteration":445,"passed_time":4.757373303,"remaining_time":0.5760048394},
{"learn":[0.0009588727977],"iteration":446,"passed_time":4.767813158,"remaining_time":0.5653111798},
{"learn":[0.0009564402158],"iteration":447,"passed_time":4.777930478,"remaining_time":0.5545812162},
{"learn":[0.0009541823077],"iteration":448,"passed_time":4.7883888,"remaining_time":0.5438927145},
{"learn":[0.0009533184634],"iteration":449,"passed_time":4.800026192,"remaining_time":0.5333362436},
{"learn":[0.0009510692596],"iteration":450,"passed_time":4.810515178,"remaining_time":0.5226502079},
{"learn":[0.0009472246214],"iteration":451,"passed_time":4.820752718,"remaining_time":0.5119383418},
{"learn":[0.0009456544401],"iteration":452,"passed_time":4.831097107,"remaining_time":0.5012396557},
{"learn":[0.0009449051169],"iteration":453,"passed_time":4.841740066,"remaining_time":0.4905727821},
{"learn":[0.0009437567087],"iteration":454,"passed_time":4.851926026,"remaining_time":0.4798608158},
{"learn":[0.0009409688906],"iteration":455,"passed_time":4.862258718,"remaining_time":0.4691653149},
{"learn":[0.0009376568073],"iteration":456,"passed_time":4.873772444,"remaining_time":0.4585825276},
{"learn":[0.0009358631281],"iteration":457,"passed_time":4.883643882,"remaining_time":0.4478450722},
{"learn":[0.0009353418911],"iteration":458,"passed_time":4.894354684,"remaining_time":0.4371863661},
{"learn":[0.0009332198905],"iteration":459,"passed_time":4.904480703,"remaining_time":0.4264765829},
{"learn":[0.0009294989337],"iteration":460,"passed_time":4.915177259,"remaining_time":0.4158175989},
{"learn":[0.0009253070672],"iteration":461,"passed_time":4.925982625,"remaining_time":0.4051674021},
{"learn":[0.0009210571161],"iteration":462,"passed_time":4.936756936,"remaining_time":0.3945140532},
{"learn":[0.0009190945451],"iteration":463,"passed_time":4.947412355,"remaining_time":0.3838509586},
{"learn":[0.0009168721661],"iteration":464,"passed_time":4.957801632,"remaining_time":0.3731678647},
{"learn":[0.0009146019919],"iteration":465,"passed_time":4.968347316,"remaining_time":0.3624974437},
{"learn":[0.0009131023814],"iteration":466,"passed_time":4.979038095,"remaining_time":0.3518378097},
{"learn":[0.0009126322873],"iteration":467,"passed_time":4.989565645,"remaining_time":0.3411668817},
{"learn":[0.0009100868873],"iteration":468,"passed_time":4.999748611,"remaining_time":0.3304737888},
{"learn":[0.0009078865461],"iteration":469,"passed_time":5.010318526,"remaining_time":0.3198075655},
{"learn":[0.0009063300382],"iteration":470,"passed_time":5.020416387,"remaining_time":0.3091126863},
{"learn":[0.0009003811832],"iteration":471,"passed_time":5.030549167,"remaining_time":0.2984224082},
{"learn":[0.0008990564272],"iteration":472,"passed_time":5.041655782,"remaining_time":0.2877900764},
{"learn":[0.0008984353904],"iteration":473,"passed_time":5.051716141,"remaining_time":0.2770983537},
{"learn":[0.0008971007738],"iteration":474,"passed_time":5.061719001,"remaining_time":0.2664062632},
{"learn":[0.0008958249992],"iteration":475,"passed_time":5.071912054,"remaining_time":0.2557266582},
{"learn":[0.0008915813277],"iteration":476,"passed_time":5.082712589,"remaining_time":0.2450783848},
{"learn":[0.0008895722248],"iteration":477,"passed_time":5.093478395,"remaining_time":0.2344278759},
{"learn":[0.0008877641184],"iteration":478,"passed_time":5.104533274,"remaining_time":0.223789559},
{"learn":[0.0008808040119],"iteration":479,"passed_time":5.116177181,"remaining_time":0.2131740492},
{"learn":[0.0008779338378],"iteration":480,"passed_time":5.127124688,"remaining_time":0.2025267548},
{"learn":[0.0008768809707],"iteration":481,"passed_time":5.138200692,"remaining_time":0.1918830134},
{"learn":[0.0008756988416],"iteration":482,"passed_time":5.149277507,"remaining_time":0.1812375106},
{"learn":[0.0008739268621],"iteration":483,"passed_time":5.160267613,"remaining_time":0.1705873591},
{"learn":[0.0008718234658],"iteration":484,"passed_time":5.170307017,"remaining_time":0.1599064026},
{"learn":[0.0008703429173],"iteration":485,"passed_time":5.18129103,"remaining_time":0.1492552972},
{"learn":[0.0008701600266],"iteration":486,"passed_time":5.191518485,"remaining_time":0.138582629},
{"learn":[0.000868657569],"iteration":487,"passed_time":5.202557807,"remaining_time":0.1279317493},
{"learn":[0.0008675871088],"iteration":488,"passed_time":5.212780761,"remaining_time":0.1172609169},
{"learn":[0.0008668988305],"iteration":489,"passed_time":5.222726494,"remaining_time":0.106586255},
{"learn":[0.0008655497554],"iteration":490,"passed_time":5.233591628,"remaining_time":0.09593141478},
{"learn":[0.0008654032881],"iteration":491,"passed_time":5.243272642,"remaining_time":0.08525646572},
{"learn":[0.0008602299691],"iteration":492,"passed_time":5.254130625,"remaining_time":0.0746022604},
{"learn":[0.0008589514626],"iteration":493,"passed_time":5.265747378,"remaining_time":0.06395644589},
{"learn":[0.0008575038739],"iteration":494,"passed_time":5.27647515,"remaining_time":0.05329772879},
{"learn":[0.000854272613],"iteration":495,"passed_time":5.287896741,"remaining_time":0.04264432856},
{"learn":[0.000851555156],"iteration":496,"passed_time":5.298791256,"remaining_time":0.03198465547},
{"learn":[0.0008502967295],"iteration":497,"passed_time":5.310142257,"remaining_time":0.02132587252},
{"learn":[0.000848938625],"iteration":498,"passed_time":5.320491174,"remaining_time":0.01066230696},
{"learn":[0.0008475983916],"iteration":499,"passed_time":5.330398912,"remaining_time":0}
]}